{
  "gitSyncId": "6a117fe9f82c2160e8de0a3e_956ba876-f2aa-4e17-860d-c018fd95fd4d",
  "id": "Workouts_UpdateWorkout",
  "pluginId": "postgres-plugin",
  "pluginType": "DB",
  "unpublishedAction": {
    "actionConfiguration": {
      "body": "UPDATE workout_templates\nSET name = {{InputWorkoutName.text}},\n    notes = {{InputNotes.text}}\nWHERE id = {{tblWorkouts.selectedRow.id}};",
      "encodeParamsToggle": true,
      "paginationType": "NONE",
      "pluginSpecifiedTemplates": [
        {
          "value": true
        }
      ],
      "timeoutInMillisecond": 10000
    },
    "confirmBeforeExecute": false,
    "datasource": {
      "id": "fitnessDB",
      "isAutoGenerated": false,
      "name": "fitnessDB",
      "pluginId": "postgres-plugin"
    },
    "dynamicBindingPathList": [
      {
        "key": "body"
      }
    ],
    "name": "UpdateWorkout",
    "pageId": "Workouts",
    "runBehaviour": "MANUAL",
    "userSetOnLoad": false
  }
}