{
  "gitSyncId": "6a117fe9f82c2160e8de0a3e_d768776a-c5e5-45ba-9609-f2495c544c6e",
  "id": "Exercises_AddExerciseMuscle",
  "pluginId": "postgres-plugin",
  "pluginType": "DB",
  "unpublishedAction": {
    "actionConfiguration": {
      "body": "INSERT INTO exercise_muscles (\n    exercise_id,\n    muscle_id,\n    role,\n    intensity\n)\nSELECT\n    {{ tblExercises.selectedRow.id }},\n    {{ SelectMuscle.selectedOptionValue }},\n    'Secondary',\n    3\nWHERE NOT EXISTS (\n    SELECT 1\n    FROM exercise_muscles\n    WHERE exercise_id = {{ tblExercises.selectedRow.id }}\n      AND muscle_id = {{ SelectMuscle.selectedOptionValue }}\n);",
      "encodeParamsToggle": true,
      "paginationType": "NONE",
      "pluginSpecifiedTemplates": [
        {
          "value": true
        }
      ],
      "timeoutInMillisecond": 10000
    },
    "confirmBeforeExecute": false,
    "datasource": {
      "id": "fitnessDB",
      "isAutoGenerated": false,
      "name": "fitnessDB",
      "pluginId": "postgres-plugin"
    },
    "dynamicBindingPathList": [
      {
        "key": "body"
      }
    ],
    "name": "AddExerciseMuscle",
    "pageId": "Exercises",
    "runBehaviour": "MANUAL",
    "userSetOnLoad": false
  }
}