{
  "gitSyncId": "6a117fe9f82c2160e8de0a3e_3de3db44-f2e4-420a-b0a5-c7361db2f66d",
  "id": "Workouts_AddExerciseToWorkout",
  "pluginId": "postgres-plugin",
  "pluginType": "DB",
  "unpublishedAction": {
    "actionConfiguration": {
      "body": "INSERT INTO template_exercises (template_id, exercise_id, default_sets, default_reps, default_weight, display_order)\nVALUES (\n    {{tblWorkouts.selectedRow.id}},\n    {{SelectExercise.value}},\n    {{InputSets.text}},\n    {{InputReps.text}},\n    {{InputWeight.text}},\n    COALESCE((SELECT MAX(display_order) + 1 FROM template_exercises WHERE template_id = {{tblWorkouts.selectedRow.id}}), 0)\n);",
      "encodeParamsToggle": true,
      "paginationType": "NONE",
      "pluginSpecifiedTemplates": [
        {
          "value": true
        }
      ],
      "timeoutInMillisecond": 10000
    },
    "confirmBeforeExecute": false,
    "datasource": {
      "id": "fitnessDB",
      "isAutoGenerated": false,
      "name": "fitnessDB",
      "pluginId": "postgres-plugin"
    },
    "dynamicBindingPathList": [
      {
        "key": "body"
      }
    ],
    "name": "AddExerciseToWorkout",
    "pageId": "Workouts",
    "runBehaviour": "MANUAL",
    "userSetOnLoad": false
  }
}